pyblocks/__init__.py
pyblocks/logging/__init__.py
pyblocks/logging/me_logger.py
pyblocks-0.1.dist-info/LICENSE
pyblocks-0.1.dist-info/METADATA
pyblocks-0.1.dist-info/WHEEL
pyblocks-0.1.dist-info/top_level.txt
pyblocks-0.1.dist-info/RECORD
