Metadata-Version: 2.1
Name: pyblocks
Version: 0.1
Summary: python utilities
Home-page: UNKNOWN
Author: Mihail Eric
Author-email: mihail911@gmail.com
License: UNKNOWN
Platform: UNKNOWN
Classifier: Programming Language :: Python :: 3
Classifier: License :: OSI Approved :: MIT License
Classifier: Operating System :: OS Independent
